real_json/GetWrappedJson.py
real_json/__init__.py
real_json-1.0.5.dist-info/LICENSE
real_json-1.0.5.dist-info/METADATA
real_json-1.0.5.dist-info/WHEEL
real_json-1.0.5.dist-info/top_level.txt
real_json-1.0.5.dist-info/RECORD
