Metadata-Version: 2.1
Name: real-json
Version: 1.0.5
Summary: Wrapper class so that you can access `dict` and `list` as easily as in Javascript
Author-email: Harold Alcala <harold.dev@gmail.com>
License: MIT License
Project-URL: Homepage, https://github.com/haalcala/python_js_json
Keywords: json,js,Javascript,wrapper
Classifier: License :: OSI Approved :: MIT License
Classifier: Programming Language :: Python
Classifier: Programming Language :: Python :: 3
Classifier: Programming Language :: JavaScript
Requires-Python: >=3.8
License-File: LICENSE
Provides-Extra: dev
Requires-Dist: black ; extra == 'dev'
Requires-Dist: bumpver ; extra == 'dev'
Requires-Dist: isort ; extra == 'dev'
Requires-Dist: pip-tools ; extra == 'dev'
Requires-Dist: pytest ; extra == 'dev'
